{
    "Ліцензії": [
        {
            "Адреса": "49089, м. Дніпропетровськ, вул. Титова, буд.36",
            "Банківська ліцензія": {
                "Перелік операцій ліцензії": {
                    "1": "залучення у вклади (депозити) коштів та банківських металів від необмеженого кола юридичних і фізичних осіб",
                    "2": "відкриття та ведення поточних (кореспондентських) рахунків клієнтів, у тому числі у банківських металах",
                    "3": "розміщення залучених у вклади (депозити), у тому числі на поточні рахунки, коштів та банківських металів від свого імені, на власних умовах та на власний ризик"
                },
                "від": "02.09.2011",
                "номер бланка": "00002",
                "номер ліцензії": "262"
            },
            "Види діяльності та фінансові послуги, які здійснюються банком на підставі його повідомлення": {
                "02.09.2011": "Емісія власних цінних паперів",
                "04.10.2012": "Переказ коштів",
                "17.10.2011": "Інкасація коштів та перевезення валютних цінностей"
            },
            "Дата відкликання": "16.01.2015",
            "Дозволи": [],
            "Код ЄДРПОУ": "37731532",
            "Назва банку": "Публічне акціонерне товариство \"ІнтерКредитБанк\"",
            "Номер банку (МФО)": "307424",
            "Підстави прийняття рішення": "Ліквідація банку"
        }
    ],
    "МФО": 307424,
    "Структура власності": [
        {
            "Дата": "2014.04.04",
            "Посилання": "http://www.bank.gov.ua/files/Shareholders/307424/307424_20140404.pdf"
        },
        {
            "Дата": "2014.01.30",
            "Посилання": "http://www.bank.gov.ua/files/Shareholders/307424/307424_20140130.pdf"
        },
        {
            "Дата": "2014.01.01",
            "Посилання": "http://www.bank.gov.ua/files/Shareholders/307424/307424_20140101.pdf"
        }
    ]
}