{
    "Код банку": 318,
    "Ліцензії": [
        {
            "Адреса": "01032, м. Київ, бульвар Тараса Шевченка, будинок 35",
            "Банківська ліцензія": {
                "Перелік операцій ліцензії": {
                    "1": "залучення у вклади (депозити) коштів та банківських металів від необмеженого кола юридичних і фізичних осіб",
                    "2": "відкриття та ведення поточних (кореспондентських) рахунків клієнтів, у тому числі у банківських металах",
                    "3": "розміщення залучених у вклади (депозити), у тому числі на поточні рахунки, коштів та банківських металів від свого імені, на власних умовах та на власний ризик"
                },
                "від": "11.11.2011",
                "номер бланка": "00140",
                "номер ліцензії": "220"
            },
            "Види діяльності та фінансові послуги, які здійснюються банком на підставі його повідомлення": {
                "14.04.2014": "Факторинг",
                "18.08.2014": "Управління фондами фінансування будівництва (ФФБ) 08.09.2014     Надання в майновий найм (оренду) індивідуального банківського сейфу"
            },
            "Дозволи": [],
            "Код ЄДРПОУ": "33305163",
            "Назва банку": "Публічне акціонерне товариство комерційний банк \"ЄВРОБАНК\"",
            "Номер банку (МФО)": "380355"
        },
        {
            "Адреса": "01032, м. Київ, бульвар Тараса Шевченка, будинок 35",
            "Банківська ліцензія": {
                "Перелік операцій ліцензії": {
                    "1Л": "Приймання вкладів (депозитів) від юридичних і фізичних осіб",
                    "1Н": "Надання гарантій і поручительств та інших зобов'язань від третіх осіб, які передбачають їх виконання у грошовій формі.",
                    "2Л": "Відкриття та ведення поточних рахунків клієнтів і банків-кореспондентів, у тому числі переказ грошових коштів з цих рахунків за допомогою платіжних інструментів та зарахування коштів на них",
                    "2Н": "Придбання або відчуження права вимоги на виконання зобов'язань у грошовій формі за поставлені товари чи надані послуги, приймаючи на себе ризик виконання таких вимог та прийом платежів (факторинг).",
                    "3Л": "Розміщення залучених коштів від свого імені, на власних умовах та на власний ризик.",
                    "3Н": "Лізинг",
                    "4Н": "Послуги з відповідального зберігання та надання в оренду (майновий найм) сейфів для зберігання цінностей та документів",
                    "5Н": "Випуск, купівля, продаж і обслуговування чеків, векселів та інших оборотних платіжних інструментів",
                    "6Н": "Випуск банківських платіжних карток і здійснення операцій з використанням цих карток",
                    "7Н": "Надання консультаційних та інформаційних послуг щодо банківських операцій"
                },
                "від": "13.10.2009",
                "номер бланка": "00408",
                "номер ліцензії": "220"
            },
            "Дозволи": [
                {
                    "Перелік операцій дозвола": {
                        "1": "Неторговельні операції з валютними цінностями.",
                        "10": "Залучення та розміщення іноземної валюти на міжнародних ринках.",
                        "11": "Торгівля іноземною валютою на валютному ринку України (за винятком валютно-обмінних операцій).",
                        "12": "Торгівля іноземною валютою на міжнародних ринках.",
                        "16": "Інші операції з валютними цінностями на валютному ринку України.",
                        "17": "Емісія власних цінних паперів.",
                        "18": "Організація купівлі та продажу цінних паперів за дорученням клієнтів.",
                        "19": "Здійснення операцій на ринку цінних паперів від свого імені (уключаючи андеррайтинг).",
                        "2": "Операції з готівковою іноземною валютою та чеками (купівля, продаж, обмін, прийняття на інкасо), що здійснюються в касах і пунктах обміну іноземної валюти банків.",
                        "23": "з інструментами грошового ринку.",
                        "24": "з інструментами, що базуються на обмінних курсах та відсотках.",
                        "25": "з фінансовими ф'ючерсами та опціонами.",
                        "27": "Депозитарна діяльність зберігача цінних паперів.",
                        "3": "Операції з готівковою іноземною валютою (купівля, продаж, обмін), що здійснюються в пунктах обміну іноземної валюти, які працюють на підставі укладених банками агентських договорів з юридичними особами-резидентами.",
                        "4": "Ведення рахунків клієнтів (резидентів і нерезидентів) в іноземній валюті та клієнтів-нерезидентів у грошовій одиниці України.",
                        "5": "Ведення кореспондентських рахунків банків (резидентів і нерезидентів) в іноземній валюті.",
                        "7": "Відкриття кореспондентських рахунків в уповноважених банках України в іноземній валюті та здійснення операцій за ними.",
                        "8": "Відкриття кореспондентських рахунків у банках (нерезидентах) в іноземній валюті та здійснення операцій за ними.",
                        "9": "Залучення та розміщення іноземної валюти на валютному ринку України."
                    },
                    "від": "13.10.2009",
                    "номер дозволу": "220-3"
                }
            ],
            "Код ЄДРПОУ": "33305163",
            "Назва банку": "Публічне акціонерне товариство комерційний банк \"ЄВРОБАНК\"",
            "Номер банку (МФО)": "380355"
        },
        {
            "Адреса": "04073, м. Київ, вул.Фрунзе, 109/2",
            "Банківська ліцензія": {
                "Перелік операцій ліцензії": {
                    "1Л": "Приймання вкладів (депозитів) від юридичних і фізичних осіб",
                    "1Н": "Надання гарантій і поручительств та інших зобов'язань від третіх осіб, які передбачають їх виконання у грошовій формі.",
                    "2Л": "Відкриття та ведення поточних рахунків клієнтів і банків-кореспондентів, у тому числі переказ грошових коштів з цих рахунків за допомогою платіжних інструментів та зарахування коштів на них",
                    "2Н": "Придбання або відчуження права вимоги на виконання зобов'язань у грошовій формі за поставлені товари чи надані послуги, приймаючи на себе ризик виконання таких вимог та прийом платежів (факторинг).",
                    "3Л": "Розміщення залучених коштів від свого імені, на власних умовах та на власний ризик.",
                    "3Н": "Лізинг",
                    "4Н": "Послуги з відповідального зберігання та надання в оренду (майновий найм) сейфів для зберігання цінностей та документів",
                    "5Н": "Випуск, купівля, продаж і обслуговування чеків, векселів та інших оборотних платіжних інструментів",
                    "6Н": "Випуск банківських платіжних карток і здійснення операцій з використанням цих карток",
                    "7Н": "Надання консультаційних та інформаційних послуг щодо банківських операцій"
                },
                "від": "25.07.2005",
                "номер бланка": "00236",
                "номер ліцензії": "220"
            },
            "Дозволи": [
                {
                    "Перелік операцій дозвола": {
                        "1": "Неторговельні операції з валютними цінностями.",
                        "12": "Емісія власних цінних паперів.",
                        "13": "Організація купівлі та продажу цінних паперів за дорученням клієнтів.",
                        "14": "Здійснення операцій на ринку цінних паперів від свого імені (включаючи андеррайтинг).",
                        "18": "з інструментами грошового ринку.",
                        "19": "з інструментами, що базуються на обмінних курсах та відсотках.",
                        "2": "Ведення рахунків клієнтів (резидентів та нерезидентів) в іноземній валюті та клієнтів-нерезидентів у грошовій одиниці України.",
                        "20": "з фінансовими ф'ючерсами та опціонами.",
                        "22": "Депозитарна діяльність зберігача цінних паперів.",
                        "3": "Ведення кореспондентських рахунків банків (резидентів і нерезидентів) в іноземній валюті.",
                        "5": "Відкриття кореспондентських рахунків в уповноважених банках України в іноземній валюті та здійснення операцій за ними.",
                        "6": "Відкриття кореспондентських рахунків у банках (нерезидентах) в іноземній валюті та здійснення операцій за ними.",
                        "7": "Залучення та розміщення іноземної валюти на валютному ринку України.",
                        "8": "Залучення та розміщення іноземної валюти на міжнародних ринках."
                    },
                    "від": "22.10.2008",
                    "номер дозволу": "220-2"
                },
                {
                    "Перелік операцій дозвола": {
                        "1": "Неторговельні операції з валютними цінностями.",
                        "12": "Емісія власних цінних паперів.",
                        "13": "Організація купівлі та продажу цінних паперів за дорученням клієнтів.",
                        "14": "Здійснення операцій на ринку цінних паперів від свого імені (включаючи андеррайтинг).",
                        "18": "з інструментами грошового ринку.",
                        "19": "з інструментами, що базуються на обмінних курсах та відсотках.",
                        "2": "Ведення рахунків клієнтів (резидентів та нерезидентів) в іноземній валюті та клієнтів-нерезидентів у грошовій одиниці України.",
                        "20": "з фінансовими ф'ючерсами та опціонами.",
                        "3": "Ведення кореспондентських рахунків банків (резидентів і нерезидентів) в іноземній валюті.",
                        "5": "Відкриття кореспондентських рахунків в уповноважених банках України в іноземній валюті та здійснення операцій за ними.",
                        "6": "Відкриття кореспондентських рахунків у банках (нерезидентах) в іноземній валюті та здійснення операцій за ними.",
                        "7": "Залучення та розміщення іноземної валюти на валютному ринку України.",
                        "8": "Залучення та розміщення іноземної валюти на міжнародних ринках."
                    },
                    "від": "25.07.2005",
                    "номер дозволу": "220-1"
                }
            ],
            "Код ЄДРПОУ": "33305163",
            "Назва банку": "Товариство з обмеженою відповідальністю комерційний банк \"ЄВРОБАНК\"",
            "Номер банку (МФО)": "380355"
        }
    ],
    "МФО": 380355,
    "Структура власності": [
        {
            "Дата": "2015.08.27",
            "Посилання": "http://www.bank.gov.ua/files/Shareholders/380355/380355_20150827.pdf"
        },
        {
            "Дата": "2015.08.13",
            "Посилання": "http://www.bank.gov.ua/files/Shareholders/380355/380355_20150813.pdf"
        },
        {
            "Дата": "2015.06.05",
            "Посилання": "http://www.bank.gov.ua/files/Shareholders/380355/380355_20150605.pdf"
        },
        {
            "Дата": "2015.03.08",
            "Посилання": "http://www.bank.gov.ua/files/Shareholders/380355/380355_20150308.pdf"
        },
        {
            "Дата": "2015.01.01",
            "Посилання": "http://www.bank.gov.ua/files/Shareholders/380355/380355_20150101.pdf"
        },
        {
            "Дата": "2014.10.31",
            "Посилання": "http://www.bank.gov.ua/files/Shareholders/380355/380355_20141031.pdf"
        },
        {
            "Дата": "2014.01.01",
            "Посилання": "http://www.bank.gov.ua/files/Shareholders/380355/380355_20140101.pdf"
        },
        {
            "Дата": "2013.01.01",
            "Посилання": "http://www.bank.gov.ua/files/Shareholders/380355/380355_20130101.pdf"
        }
    ],
    "Структурні підрозділи по датах": [
        {
            "Дата": "01.01.2008",
            "Кількість": 0
        },
        {
            "Дата": "01.01.2009",
            "Кількість": 2
        },
        {
            "Дата": "01.01.2010",
            "Кількість": 1
        },
        {
            "Дата": "01.01.2011",
            "Кількість": 1
        },
        {
            "Дата": "01.01.2012",
            "Кількість": 1
        },
        {
            "Дата": "01.01.2013",
            "Кількість": 1
        },
        {
            "Дата": "01.01.2014",
            "Кількість": 2
        },
        {
            "Дата": "01.01.2015",
            "Кількість": 2
        },
        {
            "Дата": "01.07.2015",
            "Кількість": 2
        },
        {
            "Дата": "01.08.2015",
            "Кількість": 2
        }
    ],
    "Структурні підрозділи по регіонах": [
        {
            "Кількість": 0,
            "Регіон": "Вінніцька"
        },
        {
            "Кількість": 0,
            "Регіон": "Волинська"
        },
        {
            "Кількість": 0,
            "Регіон": "Дніпропетровська"
        },
        {
            "Кількість": 0,
            "Регіон": "Донецька"
        },
        {
            "Кількість": 0,
            "Регіон": "Житомирська"
        },
        {
            "Кількість": 0,
            "Регіон": "Закарпатська"
        },
        {
            "Кількість": 0,
            "Регіон": "Запоріжська"
        },
        {
            "Кількість": 0,
            "Регіон": "Івано-Франківська"
        },
        {
            "Кількість": 2,
            "Регіон": "Київ"
        },
        {
            "Кількість": 0,
            "Регіон": "Київська"
        },
        {
            "Кількість": 0,
            "Регіон": "Кіровоградська"
        },
        {
            "Кількість": 0,
            "Регіон": "Луганська"
        },
        {
            "Кількість": 0,
            "Регіон": "Львівська"
        },
        {
            "Кількість": 0,
            "Регіон": "Миколаївська"
        },
        {
            "Кількість": 0,
            "Регіон": "Одеська"
        },
        {
            "Кількість": 0,
            "Регіон": "Полтавська"
        },
        {
            "Кількість": 0,
            "Регіон": "Рівненська"
        },
        {
            "Кількість": 0,
            "Регіон": "Сумська"
        },
        {
            "Кількість": 0,
            "Регіон": "Тернопільська"
        },
        {
            "Кількість": 0,
            "Регіон": "Харківська"
        },
        {
            "Кількість": 0,
            "Регіон": "Херсонська"
        },
        {
            "Кількість": 0,
            "Регіон": "Хмельницька"
        },
        {
            "Кількість": 0,
            "Регіон": "Черкаська"
        },
        {
            "Кількість": 0,
            "Регіон": "Чернігівська"
        },
        {
            "Кількість": 0,
            "Регіон": "Чернівецька"
        }
    ]
}